wavesis/__init__.py
wavesis/basewav.py
wavesis/frequencydomainwav.py
wavesis/rollingwav.py
wavesis/threephasewav.py
wavesis/timedomainwav.py
wavesis/utils.py
wavesis-0.0.9.dist-info/METADATA
wavesis-0.0.9.dist-info/WHEEL
wavesis-0.0.9.dist-info/top_level.txt
wavesis-0.0.9.dist-info/RECORD
